{"name":"Bowser","normalizedName":"bowser","fightCoreId":241,"moves":[{"name":"Whirling Fortress","normalizedName":"upb","hits":[],"totalFrames":79,"start":5,"end":46,"type":4,"notes":"invincible frames 1-4","characterId":0,"source":"http://meleeframedata.com/","gifUrl":"https://i.fightcore.gg/beta/bowser/upb.gif","isInterpolated":false,"sources":[{"name":"Framedata software by @NeilHarbin0","url":"https://github.com/NeilHarbin0","id":2},{"name":"GIF by Emilia \"ReelDino\" H","url":"https://drive.google.com/drive/folders/14rcZ8ed43hWOJaxQhHsB-hcAgxWubRaz?usp=sharing","id":1},{"name":"Base frame data by MeleeFrameData.com","url":"https://meleeframedata.com/","id":3},{"name":"Hitboxes from I KneeData","url":"http://ikneedata.com/","id":4}],"id":1201},{"name":"Bowser Bomb","normalizedName":"downb","hits":[],"totalFrames":106,"start":42,"end":47,"type":4,"notes":"data assumes down b lands on same height platform it started","characterId":0,"source":"http://meleeframedata.com/","gifUrl":"https://i.fightcore.gg/beta/bowser/downb.gif","isInterpolated":false,"sources":[{"name":"Hitboxes from I KneeData","url":"http://ikneedata.com/","id":4},{"name":"Base frame data by MeleeFrameData.com","url":"https://meleeframedata.com/","id":3},{"name":"GIF by Emilia \"ReelDino\" H","url":"https://drive.google.com/drive/folders/14rcZ8ed43hWOJaxQhHsB-hcAgxWubRaz?usp=sharing","id":1},{"name":"Framedata software by @NeilHarbin0","url":"https://github.com/NeilHarbin0","id":2}],"id":1202},{"name":"Fire Breath","normalizedName":"neutralb","hits":[],"totalFrames":92,"start":23,"end":62,"type":4,"notes":"frames listed are the minimum amount of frames move will be active (if you quickly tab b)","characterId":0,"source":"http://meleeframedata.com/","gifUrl":"https://i.fightcore.gg/beta/bowser/neutralb.gif","isInterpolated":false,"sources":[{"name":"Framedata software by @NeilHarbin0","url":"https://github.com/NeilHarbin0","id":2},{"name":"GIF by Emilia \"ReelDino\" H","url":"https://drive.google.com/drive/folders/14rcZ8ed43hWOJaxQhHsB-hcAgxWubRaz?usp=sharing","id":1},{"name":"Base frame data by MeleeFrameData.com","url":"https://meleeframedata.com/","id":3},{"name":"Hitboxes from I KneeData","url":"http://ikneedata.com/","id":4}],"id":1203},{"name":"Dashattack","normalizedName":"dattack","hits":[{"hitboxes":[{"name":"id0","damage":0,"angle":80,"knockbackGrowth":30,"setKnockback":0,"baseKnockback":120,"effect":"Normal","hitlagAttacker":0,"hitlagDefender":0,"hitlagAttackerCrouched":0,"hitlagDefenderCrouched":0,"shieldstun":0,"isWeightIndependent":false,"id":4508},{"name":"id1","damage":0,"angle":80,"knockbackGrowth":30,"setKnockback":0,"baseKnockback":120,"effect":"Normal","hitlagAttacker":0,"hitlagDefender":0,"hitlagAttackerCrouched":0,"hitlagDefenderCrouched":0,"shieldstun":0,"isWeightIndependent":false,"id":4509}],"start":10,"end":13,"moveId":1205,"id":550},{"hitboxes":[{"name":"id0","damage":0,"angle":80,"knockbackGrowth":30,"setKnockback":0,"baseKnockback":80,"effect":"Normal","hitlagAttacker":0,"hitlagDefender":0,"hitlagAttackerCrouched":0,"hitlagDefenderCrouched":0,"shieldstun":0,"isWeightIndependent":false,"id":4510},{"name":"id1","damage":0,"angle":80,"knockbackGrowth":30,"setKnockback":0,"baseKnockback":120,"effect":"Normal","hitlagAttacker":0,"hitlagDefender":0,"hitlagAttackerCrouched":0,"hitlagDefenderCrouched":0,"shieldstun":0,"isWeightIndependent":false,"id":4511}],"start":14,"end":17,"moveId":1205,"id":551}],"totalFrames":59,"iasa":56,"start":10,"end":17,"type":2,"notes":"weak hit frames 14-17","characterId":0,"source":"http://meleeframedata.com/","gifUrl":"https://i.fightcore.gg/beta/bowser/dattack.gif","isInterpolated":false,"sources":[{"name":"Hitboxes from I KneeData","url":"http://ikneedata.com/","id":4},{"name":"Base frame data by MeleeFrameData.com","url":"https://meleeframedata.com/","id":3},{"name":"GIF by Emilia \"ReelDino\" H","url":"https://drive.google.com/drive/folders/14rcZ8ed43hWOJaxQhHsB-hcAgxWubRaz?usp=sharing","id":1},{"name":"Framedata software by @NeilHarbin0","url":"https://github.com/NeilHarbin0","id":2}],"id":1205},{"name":"Forward Tilt","normalizedName":"ftilt","hits":[{"hitboxes":[{"name":"id0","damage":0,"angle":361,"knockbackGrowth":100,"setKnockback":0,"baseKnockback":25,"effect":"Normal","hitlagAttacker":0,"hitlagDefender":0,"hitlagAttackerCrouched":0,"hitlagDefenderCrouched":0,"shieldstun":0,"isWeightIndependent":false,"id":4495},{"name":"id1","damage":0,"angle":361,"knockbackGrowth":100,"setKnockback":0,"baseKnockback":25,"effect":"Normal","hitlagAttacker":0,"hitlagDefender":0,"hitlagAttackerCrouched":0,"hitlagDefenderCrouched":0,"shieldstun":0,"isWeightIndependent":false,"id":4496},{"name":"id2","damage":0,"angle":361,"knockbackGrowth":100,"setKnockback":0,"baseKnockback":25,"effect":"Normal","hitlagAttacker":0,"hitlagDefender":0,"hitlagAttackerCrouched":0,"hitlagDefenderCrouched":0,"shieldstun":0,"isWeightIndependent":false,"id":4497}],"start":12,"end":16,"moveId":1206,"id":545}],"totalFrames":47,"iasa":37,"start":12,"end":16,"type":1,"characterId":0,"source":"http://meleeframedata.com/","gifUrl":"https://i.fightcore.gg/beta/bowser/ftilt.gif","isInterpolated":false,"sources":[{"name":"Framedata software by @NeilHarbin0","url":"https://github.com/NeilHarbin0","id":2},{"name":"GIF by Emilia \"ReelDino\" H","url":"https://drive.google.com/drive/folders/14rcZ8ed43hWOJaxQhHsB-hcAgxWubRaz?usp=sharing","id":1},{"name":"Base frame data by MeleeFrameData.com","url":"https://meleeframedata.com/","id":3},{"name":"Hitboxes from I KneeData","url":"http://ikneedata.com/","id":4}],"id":1206},{"name":"Up Tilt","normalizedName":"utilt","hits":[{"hitboxes":[{"name":"id0","damage":0,"angle":100,"knockbackGrowth":120,"setKnockback":0,"baseKnockback":40,"effect":"Slash","hitlagAttacker":0,"hitlagDefender":0,"hitlagAttackerCrouched":0,"hitlagDefenderCrouched":0,"shieldstun":0,"isWeightIndependent":false,"id":4493},{"name":"id1","damage":0,"angle":100,"knockbackGrowth":120,"setKnockback":0,"baseKnockback":40,"effect":"Slash","hitlagAttacker":0,"hitlagDefender":0,"hitlagAttackerCrouched":0,"hitlagDefenderCrouched":0,"shieldstun":0,"isWeightIndependent":false,"id":4494}],"start":7,"end":10,"moveId":1207,"id":544}],"totalFrames":54,"iasa":50,"start":7,"end":10,"type":1,"characterId":0,"source":"http://meleeframedata.com/","gifUrl":"https://i.fightcore.gg/beta/bowser/utilt.gif","isInterpolated":false,"sources":[{"name":"Hitboxes from I KneeData","url":"http://ikneedata.com/","id":4},{"name":"Base frame data by MeleeFrameData.com","url":"https://meleeframedata.com/","id":3},{"name":"GIF by Emilia \"ReelDino\" H","url":"https://drive.google.com/drive/folders/14rcZ8ed43hWOJaxQhHsB-hcAgxWubRaz?usp=sharing","id":1},{"name":"Framedata software by @NeilHarbin0","url":"https://github.com/NeilHarbin0","id":2}],"id":1207},{"name":"Down Tilt","normalizedName":"dtilt","hits":[{"hitboxes":[{"name":"id0","damage":0,"angle":361,"knockbackGrowth":100,"setKnockback":0,"baseKnockback":15,"effect":"Slash","hitlagAttacker":0,"hitlagDefender":0,"hitlagAttackerCrouched":0,"hitlagDefenderCrouched":0,"shieldstun":0,"isWeightIndependent":false,"id":4498},{"name":"id1","damage":0,"angle":361,"knockbackGrowth":100,"setKnockback":0,"baseKnockback":15,"effect":"Slash","hitlagAttacker":0,"hitlagDefender":0,"hitlagAttackerCrouched":0,"hitlagDefenderCrouched":0,"shieldstun":0,"isWeightIndependent":false,"id":4499}],"start":14,"end":18,"moveId":1208,"id":546},{"hitboxes":[{"name":"id0","damage":0,"angle":361,"knockbackGrowth":100,"setKnockback":0,"baseKnockback":12,"effect":"Slash","hitlagAttacker":0,"hitlagDefender":0,"hitlagAttackerCrouched":0,"hitlagDefenderCrouched":0,"shieldstun":0,"isWeightIndependent":false,"id":4500},{"name":"id1","damage":0,"angle":361,"knockbackGrowth":100,"setKnockback":0,"baseKnockback":12,"effect":"Slash","hitlagAttacker":0,"hitlagDefender":0,"hitlagAttackerCrouched":0,"hitlagDefenderCrouched":0,"shieldstun":0,"isWeightIndependent":false,"id":4501}],"start":27,"end":31,"moveId":1208,"id":547}],"totalFrames":59,"iasa":55,"start":14,"end":31,"type":1,"notes":"weak hitbox frames 27-31, strong hitbox frames 14-18","characterId":0,"source":"http://meleeframedata.com/","gifUrl":"https://i.fightcore.gg/beta/bowser/dtilt.gif","isInterpolated":false,"sources":[{"name":"Framedata software by @NeilHarbin0","url":"https://github.com/NeilHarbin0","id":2},{"name":"GIF by Emilia \"ReelDino\" H","url":"https://drive.google.com/drive/folders/14rcZ8ed43hWOJaxQhHsB-hcAgxWubRaz?usp=sharing","id":1},{"name":"Base frame data by MeleeFrameData.com","url":"https://meleeframedata.com/","id":3},{"name":"Hitboxes from I KneeData","url":"http://ikneedata.com/","id":4}],"id":1208},{"name":"Forward Smash","normalizedName":"fsmash","hits":[{"hitboxes":[{"name":"id0","damage":0,"angle":361,"knockbackGrowth":100,"setKnockback":0,"baseKnockback":30,"effect":"Normal","hitlagAttacker":0,"hitlagDefender":0,"hitlagAttackerCrouched":0,"hitlagDefenderCrouched":0,"shieldstun":0,"isWeightIndependent":false,"id":4512},{"name":"id1","damage":0,"angle":60,"knockbackGrowth":100,"setKnockback":0,"baseKnockback":30,"effect":"Normal","hitlagAttacker":0,"hitlagDefender":0,"hitlagAttackerCrouched":0,"hitlagDefenderCrouched":0,"shieldstun":0,"isWeightIndependent":false,"id":4513}],"start":29,"end":33,"moveId":1209,"id":552}],"totalFrames":69,"iasa":66,"start":29,"end":33,"type":2,"characterId":0,"source":"http://meleeframedata.com/","gifUrl":"https://i.fightcore.gg/beta/bowser/fsmash.gif","isInterpolated":false,"sources":[{"name":"Hitboxes from I KneeData","url":"http://ikneedata.com/","id":4},{"name":"Base frame data by MeleeFrameData.com","url":"https://meleeframedata.com/","id":3},{"name":"GIF by Emilia \"ReelDino\" H","url":"https://drive.google.com/drive/folders/14rcZ8ed43hWOJaxQhHsB-hcAgxWubRaz?usp=sharing","id":1},{"name":"Framedata software by @NeilHarbin0","url":"https://github.com/NeilHarbin0","id":2}],"id":1209},{"name":"Up Smash","normalizedName":"usmash","hits":[{"hitboxes":[{"name":"id0","damage":0,"angle":90,"knockbackGrowth":86,"setKnockback":0,"baseKnockback":40,"effect":"Slash","hitlagAttacker":0,"hitlagDefender":0,"hitlagAttackerCrouched":0,"hitlagDefenderCrouched":0,"shieldstun":0,"isWeightIndependent":false,"id":4514},{"name":"id1","damage":0,"angle":90,"knockbackGrowth":86,"setKnockback":0,"baseKnockback":40,"effect":"Slash","hitlagAttacker":0,"hitlagDefender":0,"hitlagAttackerCrouched":0,"hitlagDefenderCrouched":0,"shieldstun":0,"isWeightIndependent":false,"id":4515}],"start":16,"end":21,"moveId":1210,"id":553},{"hitboxes":[{"name":"id0","damage":0,"angle":74,"knockbackGrowth":100,"setKnockback":0,"baseKnockback":60,"effect":"Normal","hitlagAttacker":0,"hitlagDefender":0,"hitlagAttackerCrouched":0,"hitlagDefenderCrouched":0,"shieldstun":0,"isWeightIndependent":false,"id":4516},{"name":"id1","damage":0,"angle":74,"knockbackGrowth":100,"setKnockback":0,"baseKnockback":60,"effect":"Normal","hitlagAttacker":0,"hitlagDefender":0,"hitlagAttackerCrouched":0,"hitlagDefenderCrouched":0,"shieldstun":0,"isWeightIndependent":false,"id":4517}],"start":30,"end":30,"moveId":1210,"id":554}],"totalFrames":59,"iasa":53,"start":16,"end":30,"type":2,"notes":"strong hit frames 16-21, can also do 17% damage. weak hit frame 30 and has 7 frames shield stun","characterId":0,"source":"http://meleeframedata.com/","gifUrl":"https://i.fightcore.gg/beta/bowser/usmash.gif","isInterpolated":false,"sources":[{"name":"Framedata software by @NeilHarbin0","url":"https://github.com/NeilHarbin0","id":2},{"name":"GIF by Emilia \"ReelDino\" H","url":"https://drive.google.com/drive/folders/14rcZ8ed43hWOJaxQhHsB-hcAgxWubRaz?usp=sharing","id":1},{"name":"Base frame data by MeleeFrameData.com","url":"https://meleeframedata.com/","id":3},{"name":"Hitboxes from I KneeData","url":"http://ikneedata.com/","id":4}],"id":1210},{"name":"Down Smash","normalizedName":"dsmash","hits":[{"hitboxes":[{"name":"id0","damage":0,"angle":150,"knockbackGrowth":50,"setKnockback":0,"baseKnockback":40,"effect":"Slash","hitlagAttacker":0,"hitlagDefender":0,"hitlagAttackerCrouched":0,"hitlagDefenderCrouched":0,"shieldstun":0,"isWeightIndependent":false,"id":4518},{"name":"id1","damage":0,"angle":150,"knockbackGrowth":50,"setKnockback":0,"baseKnockback":40,"effect":"Slash","hitlagAttacker":0,"hitlagDefender":0,"hitlagAttackerCrouched":0,"hitlagDefenderCrouched":0,"shieldstun":0,"isWeightIndependent":false,"id":4519},{"name":"id2","damage":0,"angle":190,"knockbackGrowth":50,"setKnockback":0,"baseKnockback":40,"effect":"Slash","hitlagAttacker":0,"hitlagDefender":0,"hitlagAttackerCrouched":0,"hitlagDefenderCrouched":0,"shieldstun":0,"isWeightIndependent":false,"id":4520},{"name":"id3","damage":0,"angle":190,"knockbackGrowth":50,"setKnockback":0,"baseKnockback":40,"effect":"Slash","hitlagAttacker":0,"hitlagDefender":0,"hitlagAttackerCrouched":0,"hitlagDefenderCrouched":0,"shieldstun":0,"isWeightIndependent":false,"id":4521}],"start":14,"end":15,"moveId":1211,"id":555},{"hitboxes":[{"name":"id0","damage":0,"angle":150,"knockbackGrowth":50,"setKnockback":0,"baseKnockback":40,"effect":"Slash","hitlagAttacker":0,"hitlagDefender":0,"hitlagAttackerCrouched":0,"hitlagDefenderCrouched":0,"shieldstun":0,"isWeightIndependent":false,"id":4522},{"name":"id1","damage":0,"angle":150,"knockbackGrowth":50,"setKnockback":0,"baseKnockback":40,"effect":"Slash","hitlagAttacker":0,"hitlagDefender":0,"hitlagAttackerCrouched":0,"hitlagDefenderCrouched":0,"shieldstun":0,"isWeightIndependent":false,"id":4523},{"name":"id2","damage":0,"angle":190,"knockbackGrowth":50,"setKnockback":0,"baseKnockback":40,"effect":"Slash","hitlagAttacker":0,"hitlagDefender":0,"hitlagAttackerCrouched":0,"hitlagDefenderCrouched":0,"shieldstun":0,"isWeightIndependent":false,"id":4524},{"name":"id3","damage":0,"angle":190,"knockbackGrowth":50,"setKnockback":0,"baseKnockback":40,"effect":"Slash","hitlagAttacker":0,"hitlagDefender":0,"hitlagAttackerCrouched":0,"hitlagDefenderCrouched":0,"shieldstun":0,"isWeightIndependent":false,"id":4525}],"start":17,"end":18,"moveId":1211,"id":556},{"hitboxes":[{"name":"id0","damage":0,"angle":150,"knockbackGrowth":50,"setKnockback":0,"baseKnockback":40,"effect":"Slash","hitlagAttacker":0,"hitlagDefender":0,"hitlagAttackerCrouched":0,"hitlagDefenderCrouched":0,"shieldstun":0,"isWeightIndependent":false,"id":4526},{"name":"id1","damage":0,"angle":150,"knockbackGrowth":50,"setKnockback":0,"baseKnockback":40,"effect":"Slash","hitlagAttacker":0,"hitlagDefender":0,"hitlagAttackerCrouched":0,"hitlagDefenderCrouched":0,"shieldstun":0,"isWeightIndependent":false,"id":4527},{"name":"id2","damage":0,"angle":190,"knockbackGrowth":50,"setKnockback":0,"baseKnockback":40,"effect":"Slash","hitlagAttacker":0,"hitlagDefender":0,"hitlagAttackerCrouched":0,"hitlagDefenderCrouched":0,"shieldstun":0,"isWeightIndependent":false,"id":4528},{"name":"id3","damage":0,"angle":190,"knockbackGrowth":50,"setKnockback":0,"baseKnockback":40,"effect":"Slash","hitlagAttacker":0,"hitlagDefender":0,"hitlagAttackerCrouched":0,"hitlagDefenderCrouched":0,"shieldstun":0,"isWeightIndependent":false,"id":4529}],"start":20,"end":21,"moveId":1211,"id":557},{"hitboxes":[{"name":"id0","damage":0,"angle":150,"knockbackGrowth":50,"setKnockback":0,"baseKnockback":40,"effect":"Slash","hitlagAttacker":0,"hitlagDefender":0,"hitlagAttackerCrouched":0,"hitlagDefenderCrouched":0,"shieldstun":0,"isWeightIndependent":false,"id":4530},{"name":"id1","damage":0,"angle":150,"knockbackGrowth":50,"setKnockback":0,"baseKnockback":40,"effect":"Slash","hitlagAttacker":0,"hitlagDefender":0,"hitlagAttackerCrouched":0,"hitlagDefenderCrouched":0,"shieldstun":0,"isWeightIndependent":false,"id":4531},{"name":"id2","damage":0,"angle":190,"knockbackGrowth":50,"setKnockback":0,"baseKnockback":40,"effect":"Slash","hitlagAttacker":0,"hitlagDefender":0,"hitlagAttackerCrouched":0,"hitlagDefenderCrouched":0,"shieldstun":0,"isWeightIndependent":false,"id":4532},{"name":"id3","damage":0,"angle":190,"knockbackGrowth":50,"setKnockback":0,"baseKnockback":40,"effect":"Slash","hitlagAttacker":0,"hitlagDefender":0,"hitlagAttackerCrouched":0,"hitlagDefenderCrouched":0,"shieldstun":0,"isWeightIndependent":false,"id":4533}],"start":23,"end":24,"moveId":1211,"id":558},{"hitboxes":[{"name":"id0","damage":0,"angle":150,"knockbackGrowth":50,"setKnockback":0,"baseKnockback":40,"effect":"Slash","hitlagAttacker":0,"hitlagDefender":0,"hitlagAttackerCrouched":0,"hitlagDefenderCrouched":0,"shieldstun":0,"isWeightIndependent":false,"id":4534},{"name":"id1","damage":0,"angle":150,"knockbackGrowth":50,"setKnockback":0,"baseKnockback":40,"effect":"Slash","hitlagAttacker":0,"hitlagDefender":0,"hitlagAttackerCrouched":0,"hitlagDefenderCrouched":0,"shieldstun":0,"isWeightIndependent":false,"id":4535},{"name":"id2","damage":0,"angle":190,"knockbackGrowth":50,"setKnockback":0,"baseKnockback":40,"effect":"Slash","hitlagAttacker":0,"hitlagDefender":0,"hitlagAttackerCrouched":0,"hitlagDefenderCrouched":0,"shieldstun":0,"isWeightIndependent":false,"id":4536},{"name":"id3","damage":0,"angle":190,"knockbackGrowth":50,"setKnockback":0,"baseKnockback":40,"effect":"Slash","hitlagAttacker":0,"hitlagDefender":0,"hitlagAttackerCrouched":0,"hitlagDefenderCrouched":0,"shieldstun":0,"isWeightIndependent":false,"id":4537}],"start":26,"end":27,"moveId":1211,"id":559},{"hitboxes":[{"name":"id0","damage":0,"angle":150,"knockbackGrowth":50,"setKnockback":0,"baseKnockback":40,"effect":"Slash","hitlagAttacker":0,"hitlagDefender":0,"hitlagAttackerCrouched":0,"hitlagDefenderCrouched":0,"shieldstun":0,"isWeightIndependent":false,"id":4538},{"name":"id1","damage":0,"angle":150,"knockbackGrowth":50,"setKnockback":0,"baseKnockback":40,"effect":"Slash","hitlagAttacker":0,"hitlagDefender":0,"hitlagAttackerCrouched":0,"hitlagDefenderCrouched":0,"shieldstun":0,"isWeightIndependent":false,"id":4539},{"name":"id2","damage":0,"angle":190,"knockbackGrowth":50,"setKnockback":0,"baseKnockback":40,"effect":"Slash","hitlagAttacker":0,"hitlagDefender":0,"hitlagAttackerCrouched":0,"hitlagDefenderCrouched":0,"shieldstun":0,"isWeightIndependent":false,"id":4540},{"name":"id3","damage":0,"angle":190,"knockbackGrowth":50,"setKnockback":0,"baseKnockback":40,"effect":"Slash","hitlagAttacker":0,"hitlagDefender":0,"hitlagAttackerCrouched":0,"hitlagDefenderCrouched":0,"shieldstun":0,"isWeightIndependent":false,"id":4541}],"start":29,"end":30,"moveId":1211,"id":560},{"hitboxes":[{"name":"id0","damage":0,"angle":150,"knockbackGrowth":50,"setKnockback":0,"baseKnockback":40,"effect":"Slash","hitlagAttacker":0,"hitlagDefender":0,"hitlagAttackerCrouched":0,"hitlagDefenderCrouched":0,"shieldstun":0,"isWeightIndependent":false,"id":4542},{"name":"id1","damage":0,"angle":150,"knockbackGrowth":50,"setKnockback":0,"baseKnockback":40,"effect":"Slash","hitlagAttacker":0,"hitlagDefender":0,"hitlagAttackerCrouched":0,"hitlagDefenderCrouched":0,"shieldstun":0,"isWeightIndependent":false,"id":4543},{"name":"id2","damage":0,"angle":190,"knockbackGrowth":50,"setKnockback":0,"baseKnockback":40,"effect":"Slash","hitlagAttacker":0,"hitlagDefender":0,"hitlagAttackerCrouched":0,"hitlagDefenderCrouched":0,"shieldstun":0,"isWeightIndependent":false,"id":4544},{"name":"id3","damage":0,"angle":190,"knockbackGrowth":50,"setKnockback":0,"baseKnockback":40,"effect":"Slash","hitlagAttacker":0,"hitlagDefender":0,"hitlagAttackerCrouched":0,"hitlagDefenderCrouched":0,"shieldstun":0,"isWeightIndependent":false,"id":4545}],"start":32,"end":33,"moveId":1211,"id":561},{"hitboxes":[{"name":"id0","damage":0,"angle":90,"knockbackGrowth":140,"setKnockback":0,"baseKnockback":40,"effect":"Slash","hitlagAttacker":0,"hitlagDefender":0,"hitlagAttackerCrouched":0,"hitlagDefenderCrouched":0,"shieldstun":0,"isWeightIndependent":false,"id":4546}],"start":35,"end":35,"moveId":1211,"id":562}],"totalFrames":69,"iasa":68,"start":14,"end":35,"type":2,"notes":"7 weak hits followed by strong hit at frame 35","characterId":0,"source":"http://meleeframedata.com/","gifUrl":"https://i.fightcore.gg/beta/bowser/dsmash.gif","isInterpolated":false,"sources":[{"name":"Hitboxes from I KneeData","url":"http://ikneedata.com/","id":4},{"name":"Base frame data by MeleeFrameData.com","url":"https://meleeframedata.com/","id":3},{"name":"GIF by Emilia \"ReelDino\" H","url":"https://drive.google.com/drive/folders/14rcZ8ed43hWOJaxQhHsB-hcAgxWubRaz?usp=sharing","id":1},{"name":"Framedata software by @NeilHarbin0","url":"https://github.com/NeilHarbin0","id":2}],"id":1211},{"name":"Neutral Air","normalizedName":"nair","hits":[{"hitboxes":[{"name":"id0","damage":0,"angle":361,"knockbackGrowth":80,"setKnockback":0,"baseKnockback":20,"effect":"Normal","hitlagAttacker":0,"hitlagDefender":0,"hitlagAttackerCrouched":0,"hitlagDefenderCrouched":0,"shieldstun":0,"isWeightIndependent":false,"id":4547}],"start":8,"end":23,"moveId":1212,"id":563}],"landLag":15,"lCanceledLandLag":7,"totalFrames":49,"iasa":48,"autoCancelBefore":8,"autoCancelAfter":39,"start":8,"end":23,"type":3,"characterId":0,"source":"http://meleeframedata.com/","gifUrl":"https://i.fightcore.gg/beta/bowser/nair.gif","isInterpolated":false,"sources":[{"name":"Framedata software by @NeilHarbin0","url":"https://github.com/NeilHarbin0","id":2},{"name":"GIF by Emilia \"ReelDino\" H","url":"https://drive.google.com/drive/folders/14rcZ8ed43hWOJaxQhHsB-hcAgxWubRaz?usp=sharing","id":1},{"name":"Base frame data by MeleeFrameData.com","url":"https://meleeframedata.com/","id":3},{"name":"Hitboxes from I KneeData","url":"http://ikneedata.com/","id":4}],"id":1212},{"name":"Forward Air","normalizedName":"fair","hits":[{"hitboxes":[{"name":"id0","damage":0,"angle":361,"knockbackGrowth":80,"setKnockback":0,"baseKnockback":50,"effect":"Normal","hitlagAttacker":0,"hitlagDefender":0,"hitlagAttackerCrouched":0,"hitlagDefenderCrouched":0,"shieldstun":0,"isWeightIndependent":false,"id":4548},{"name":"id1","damage":0,"angle":361,"knockbackGrowth":80,"setKnockback":0,"baseKnockback":50,"effect":"Normal","hitlagAttacker":0,"hitlagDefender":0,"hitlagAttackerCrouched":0,"hitlagDefenderCrouched":0,"shieldstun":0,"isWeightIndependent":false,"id":4549},{"name":"id2","damage":0,"angle":361,"knockbackGrowth":80,"setKnockback":0,"baseKnockback":50,"effect":"Normal","hitlagAttacker":0,"hitlagDefender":0,"hitlagAttackerCrouched":0,"hitlagDefenderCrouched":0,"shieldstun":0,"isWeightIndependent":false,"id":4550}],"start":8,"end":11,"moveId":1213,"id":564}],"landLag":30,"lCanceledLandLag":15,"totalFrames":45,"iasa":42,"autoCancelBefore":9,"autoCancelAfter":30,"start":8,"end":11,"type":3,"characterId":0,"source":"http://meleeframedata.com/","gifUrl":"https://i.fightcore.gg/beta/bowser/fair.gif","isInterpolated":false,"sources":[{"name":"Hitboxes from I KneeData","url":"http://ikneedata.com/","id":4},{"name":"Base frame data by MeleeFrameData.com","url":"https://meleeframedata.com/","id":3},{"name":"GIF by Emilia \"ReelDino\" H","url":"https://drive.google.com/drive/folders/14rcZ8ed43hWOJaxQhHsB-hcAgxWubRaz?usp=sharing","id":1},{"name":"Framedata software by @NeilHarbin0","url":"https://github.com/NeilHarbin0","id":2}],"id":1213},{"name":"Back Air","normalizedName":"bair","hits":[],"landLag":35,"lCanceledLandLag":17,"totalFrames":49,"autoCancelBefore":9,"autoCancelAfter":44,"start":9,"end":17,"type":3,"notes":"weak hit frames 11-17","characterId":0,"source":"http://meleeframedata.com/","gifUrl":"https://i.fightcore.gg/beta/bowser/bair.gif","isInterpolated":false,"sources":[{"name":"Framedata software by @NeilHarbin0","url":"https://github.com/NeilHarbin0","id":2},{"name":"GIF by Emilia \"ReelDino\" H","url":"https://drive.google.com/drive/folders/14rcZ8ed43hWOJaxQhHsB-hcAgxWubRaz?usp=sharing","id":1},{"name":"Base frame data by MeleeFrameData.com","url":"https://meleeframedata.com/","id":3},{"name":"Hitboxes from I KneeData","url":"http://ikneedata.com/","id":4}],"id":1214},{"name":"Up Air","normalizedName":"uair","hits":[{"hitboxes":[{"name":"id0","damage":0,"angle":85,"knockbackGrowth":100,"setKnockback":0,"baseKnockback":50,"effect":"Normal","hitlagAttacker":0,"hitlagDefender":0,"hitlagAttackerCrouched":0,"hitlagDefenderCrouched":0,"shieldstun":0,"isWeightIndependent":false,"id":4561}],"start":22,"end":25,"moveId":1215,"id":575}],"landLag":30,"lCanceledLandLag":15,"totalFrames":47,"iasa":45,"autoCancelBefore":10,"autoCancelAfter":39,"start":22,"end":25,"type":3,"characterId":0,"source":"http://meleeframedata.com/","gifUrl":"https://i.fightcore.gg/beta/bowser/uair.gif","isInterpolated":false,"sources":[{"name":"Hitboxes from I KneeData","url":"http://ikneedata.com/","id":4},{"name":"Base frame data by MeleeFrameData.com","url":"https://meleeframedata.com/","id":3},{"name":"GIF by Emilia \"ReelDino\" H","url":"https://drive.google.com/drive/folders/14rcZ8ed43hWOJaxQhHsB-hcAgxWubRaz?usp=sharing","id":1},{"name":"Framedata software by @NeilHarbin0","url":"https://github.com/NeilHarbin0","id":2}],"id":1215},{"name":"Down Air","normalizedName":"dair","hits":[{"hitboxes":[{"name":"id0","damage":0,"angle":80,"knockbackGrowth":100,"setKnockback":10,"baseKnockback":0,"effect":"Slash","hitlagAttacker":0,"hitlagDefender":0,"hitlagAttackerCrouched":0,"hitlagDefenderCrouched":0,"shieldstun":0,"isWeightIndependent":false,"id":4551}],"start":14,"end":15,"moveId":1216,"id":565},{"hitboxes":[{"name":"id0","damage":0,"angle":80,"knockbackGrowth":100,"setKnockback":10,"baseKnockback":0,"effect":"Slash","hitlagAttacker":0,"hitlagDefender":0,"hitlagAttackerCrouched":0,"hitlagDefenderCrouched":0,"shieldstun":0,"isWeightIndependent":false,"id":4552}],"start":17,"end":18,"moveId":1216,"id":566},{"hitboxes":[{"name":"id0","damage":0,"angle":80,"knockbackGrowth":100,"setKnockback":10,"baseKnockback":0,"effect":"Slash","hitlagAttacker":0,"hitlagDefender":0,"hitlagAttackerCrouched":0,"hitlagDefenderCrouched":0,"shieldstun":0,"isWeightIndependent":false,"id":4553}],"start":20,"end":21,"moveId":1216,"id":567},{"hitboxes":[{"name":"id0","damage":0,"angle":80,"knockbackGrowth":100,"setKnockback":10,"baseKnockback":0,"effect":"Slash","hitlagAttacker":0,"hitlagDefender":0,"hitlagAttackerCrouched":0,"hitlagDefenderCrouched":0,"shieldstun":0,"isWeightIndependent":false,"id":4554}],"start":23,"end":24,"moveId":1216,"id":568},{"hitboxes":[{"name":"id0","damage":0,"angle":80,"knockbackGrowth":100,"setKnockback":10,"baseKnockback":0,"effect":"Slash","hitlagAttacker":0,"hitlagDefender":0,"hitlagAttackerCrouched":0,"hitlagDefenderCrouched":0,"shieldstun":0,"isWeightIndependent":false,"id":4555}],"start":26,"end":27,"moveId":1216,"id":569},{"hitboxes":[{"name":"id0","damage":0,"angle":80,"knockbackGrowth":100,"setKnockback":10,"baseKnockback":0,"effect":"Slash","hitlagAttacker":0,"hitlagDefender":0,"hitlagAttackerCrouched":0,"hitlagDefenderCrouched":0,"shieldstun":0,"isWeightIndependent":false,"id":4556}],"start":29,"end":30,"moveId":1216,"id":570},{"hitboxes":[{"name":"id0","damage":0,"angle":80,"knockbackGrowth":100,"setKnockback":10,"baseKnockback":0,"effect":"Slash","hitlagAttacker":0,"hitlagDefender":0,"hitlagAttackerCrouched":0,"hitlagDefenderCrouched":0,"shieldstun":0,"isWeightIndependent":false,"id":4557}],"start":32,"end":33,"moveId":1216,"id":571},{"hitboxes":[{"name":"id0","damage":0,"angle":80,"knockbackGrowth":100,"setKnockback":10,"baseKnockback":0,"effect":"Slash","hitlagAttacker":0,"hitlagDefender":0,"hitlagAttackerCrouched":0,"hitlagDefenderCrouched":0,"shieldstun":0,"isWeightIndependent":false,"id":4558}],"start":35,"end":36,"moveId":1216,"id":572},{"hitboxes":[{"name":"id0","damage":0,"angle":80,"knockbackGrowth":100,"setKnockback":10,"baseKnockback":0,"effect":"Slash","hitlagAttacker":0,"hitlagDefender":0,"hitlagAttackerCrouched":0,"hitlagDefenderCrouched":0,"shieldstun":0,"isWeightIndependent":false,"id":4559}],"start":38,"end":39,"moveId":1216,"id":573},{"hitboxes":[{"name":"id0","damage":0,"angle":80,"knockbackGrowth":100,"setKnockback":10,"baseKnockback":0,"effect":"Slash","hitlagAttacker":0,"hitlagDefender":0,"hitlagAttackerCrouched":0,"hitlagDefenderCrouched":0,"shieldstun":0,"isWeightIndependent":false,"id":4560}],"start":41,"end":42,"moveId":1216,"id":574}],"landLag":40,"lCanceledLandLag":20,"totalFrames":79,"iasa":78,"autoCancelBefore":14,"autoCancelAfter":69,"start":14,"end":42,"type":3,"notes":"10 hits, 2 frames each","characterId":0,"source":"http://meleeframedata.com/","gifUrl":"https://i.fightcore.gg/beta/bowser/dair.gif","isInterpolated":false,"sources":[{"name":"Framedata software by @NeilHarbin0","url":"https://github.com/NeilHarbin0","id":2},{"name":"GIF by Emilia \"ReelDino\" H","url":"https://drive.google.com/drive/folders/14rcZ8ed43hWOJaxQhHsB-hcAgxWubRaz?usp=sharing","id":1},{"name":"Base frame data by MeleeFrameData.com","url":"https://meleeframedata.com/","id":3},{"name":"Hitboxes from I KneeData","url":"http://ikneedata.com/","id":4}],"id":1216},{"name":"Koopa Klaw","normalizedName":"sideb","hits":[],"totalFrames":59,"start":16,"end":18,"type":4,"notes":"scratch can do 12, 10, or 8% damage. when grabbed, \"bite\" does 4%, forward throw does 13%, and back throw does 9%","characterId":0,"source":"http://meleeframedata.com/","gifUrl":"https://i.fightcore.gg/beta/bowser/sideb.gif","isInterpolated":false,"sources":[{"name":"Hitboxes from I KneeData","url":"http://ikneedata.com/","id":4},{"name":"Base frame data by MeleeFrameData.com","url":"https://meleeframedata.com/","id":3},{"name":"GIF by Emilia \"ReelDino\" H","url":"https://drive.google.com/drive/folders/14rcZ8ed43hWOJaxQhHsB-hcAgxWubRaz?usp=sharing","id":1},{"name":"Framedata software by @NeilHarbin0","url":"https://github.com/NeilHarbin0","id":2}],"id":1218},{"name":"Edge attack","normalizedName":"edge","hits":[],"totalFrames":0,"type":0,"characterId":0,"source":"http://meleeframedata.com/","isInterpolated":false,"sources":[{"name":"Base frame data by MeleeFrameData.com","url":"https://meleeframedata.com/","id":3},{"name":"Hitboxes from I KneeData","url":"http://ikneedata.com/","id":4}],"id":1219},{"name":"unknown","normalizedName":"unknown","hits":[],"totalFrames":0,"type":0,"characterId":0,"source":"http://meleeframedata.com/","isInterpolated":false,"sources":[{"name":"Hitboxes from I KneeData","url":"http://ikneedata.com/","id":4},{"name":"Base frame data by MeleeFrameData.com","url":"https://meleeframedata.com/","id":3}],"id":1220},{"name":"Pummel","normalizedName":"pummel","hits":[{"hitboxes":[{"name":"id0","damage":0,"angle":80,"knockbackGrowth":100,"setKnockback":30,"baseKnockback":0,"effect":"Normal","hitlagAttacker":0,"hitlagDefender":0,"hitlagAttackerCrouched":0,"hitlagDefenderCrouched":0,"shieldstun":0,"isWeightIndependent":false,"id":4568}],"start":9,"end":9,"moveId":1241,"id":578}],"totalFrames":0,"type":0,"characterId":0,"source":"http://meleeframedata.com/","isInterpolated":false,"sources":[{"name":"Base frame data by MeleeFrameData.com","url":"https://meleeframedata.com/","id":3},{"name":"Hitboxes from I KneeData","url":"http://ikneedata.com/","id":4}],"id":1241},{"name":"Back throw","normalizedName":"bthrow","hits":[],"totalFrames":39,"start":0,"end":0,"type":6,"characterId":0,"source":"http://meleeframedata.com/","isInterpolated":false,"sources":[{"name":"Hitboxes from I KneeData","url":"http://ikneedata.com/","id":4},{"name":"Base frame data by MeleeFrameData.com","url":"https://meleeframedata.com/","id":3}],"id":1242},{"name":"Forward throw","normalizedName":"fthrow","hits":[],"totalFrames":59,"start":0,"end":0,"type":6,"characterId":0,"source":"http://meleeframedata.com/","isInterpolated":false,"sources":[{"name":"Base frame data by MeleeFrameData.com","url":"https://meleeframedata.com/","id":3},{"name":"Hitboxes from I KneeData","url":"http://ikneedata.com/","id":4}],"id":1261},{"name":"Up throw","normalizedName":"uthrow","hits":[],"totalFrames":43,"start":11,"end":28,"type":6,"characterId":0,"source":"http://meleeframedata.com/","isInterpolated":false,"sources":[{"name":"Hitboxes from I KneeData","url":"http://ikneedata.com/","id":4},{"name":"Base frame data by MeleeFrameData.com","url":"https://meleeframedata.com/","id":3}],"id":1264},{"name":"Down throw","normalizedName":"dthrow","hits":[],"totalFrames":39,"start":0,"end":0,"type":6,"characterId":0,"source":"http://meleeframedata.com/","isInterpolated":false,"sources":[{"name":"Base frame data by MeleeFrameData.com","url":"https://meleeframedata.com/","id":3},{"name":"Hitboxes from I KneeData","url":"http://ikneedata.com/","id":4}],"id":1265},{"name":"Roll backwards","normalizedName":"rollbackwards","hits":[],"totalFrames":39,"start":4,"end":19,"type":5,"characterId":0,"source":"http://meleeframedata.com/","gifUrl":"https://i.fightcore.gg/beta/bowser/rollbackwards.gif","isInterpolated":false,"sources":[{"name":"Base frame data by MeleeFrameData.com","url":"https://meleeframedata.com/","id":3},{"name":"Framedata software by @NeilHarbin0","url":"https://github.com/NeilHarbin0","id":2},{"name":"GIF by Emilia \"ReelDino\" H","url":"https://drive.google.com/drive/folders/14rcZ8ed43hWOJaxQhHsB-hcAgxWubRaz?usp=sharing","id":1}],"id":1442},{"name":"Roll forwards","normalizedName":"rollforward","hits":[],"totalFrames":39,"start":4,"end":19,"type":5,"characterId":0,"source":"http://meleeframedata.com/","gifUrl":"https://i.fightcore.gg/beta/bowser/rollforward.gif","isInterpolated":false,"sources":[{"name":"GIF by Emilia \"ReelDino\" H","url":"https://drive.google.com/drive/folders/14rcZ8ed43hWOJaxQhHsB-hcAgxWubRaz?usp=sharing","id":1},{"name":"Framedata software by @NeilHarbin0","url":"https://github.com/NeilHarbin0","id":2},{"name":"Base frame data by MeleeFrameData.com","url":"https://meleeframedata.com/","id":3}],"id":1443},{"name":"Spotdodge","normalizedName":"spotdodge","hits":[],"totalFrames":42,"start":4,"end":24,"type":5,"characterId":0,"source":"http://meleeframedata.com/","gifUrl":"https://i.fightcore.gg/beta/bowser/spotdodge.gif","isInterpolated":false,"sources":[{"name":"Base frame data by MeleeFrameData.com","url":"https://meleeframedata.com/","id":3},{"name":"Framedata software by @NeilHarbin0","url":"https://github.com/NeilHarbin0","id":2},{"name":"GIF by Emilia \"ReelDino\" H","url":"https://drive.google.com/drive/folders/14rcZ8ed43hWOJaxQhHsB-hcAgxWubRaz?usp=sharing","id":1}],"id":1444},{"name":"Airdodge","normalizedName":"airdodge","hits":[],"totalFrames":49,"start":2,"type":5,"characterId":0,"source":"http://meleeframedata.com/","gifUrl":"https://i.fightcore.gg/beta/bowser/airdodge.gif","isInterpolated":false,"sources":[{"name":"GIF by Emilia \"ReelDino\" H","url":"https://drive.google.com/drive/folders/14rcZ8ed43hWOJaxQhHsB-hcAgxWubRaz?usp=sharing","id":1},{"name":"Framedata software by @NeilHarbin0","url":"https://github.com/NeilHarbin0","id":2},{"name":"Base frame data by MeleeFrameData.com","url":"https://meleeframedata.com/","id":3}],"id":1445},{"name":"Jab 1","normalizedName":"jab1","hits":[{"hitboxes":[{"name":"id0","damage":0,"angle":83,"knockbackGrowth":100,"setKnockback":20,"baseKnockback":0,"effect":"Slash","hitlagAttacker":0,"hitlagDefender":0,"hitlagAttackerCrouched":0,"hitlagDefenderCrouched":0,"shieldstun":0,"isWeightIndependent":false,"id":4502},{"name":"id1","damage":0,"angle":83,"knockbackGrowth":100,"setKnockback":20,"baseKnockback":0,"effect":"Slash","hitlagAttacker":0,"hitlagDefender":0,"hitlagAttackerCrouched":0,"hitlagDefenderCrouched":0,"shieldstun":0,"isWeightIndependent":false,"id":4503},{"name":"id2","damage":0,"angle":83,"knockbackGrowth":100,"setKnockback":20,"baseKnockback":0,"effect":"Slash","hitlagAttacker":0,"hitlagDefender":0,"hitlagAttackerCrouched":0,"hitlagDefenderCrouched":0,"shieldstun":0,"isWeightIndependent":false,"id":4504}],"start":7,"end":9,"moveId":1532,"id":548}],"totalFrames":24,"iasa":21,"start":7,"end":9,"type":2,"characterId":0,"source":"http://meleeframedata.com/","gifUrl":"https://i.fightcore.gg/beta/bowser/jab1.gif","isInterpolated":false,"sources":[{"name":"Base frame data by MeleeFrameData.com","url":"https://meleeframedata.com/","id":3},{"name":"Framedata software by @NeilHarbin0","url":"https://github.com/NeilHarbin0","id":2},{"name":"GIF by Emilia \"ReelDino\" H","url":"https://drive.google.com/drive/folders/14rcZ8ed43hWOJaxQhHsB-hcAgxWubRaz?usp=sharing","id":1},{"name":"Hitboxes from I KneeData","url":"http://ikneedata.com/","id":4}],"id":1532},{"name":"Jab 2","normalizedName":"jab2","hits":[{"hitboxes":[{"name":"id0","damage":0,"angle":361,"knockbackGrowth":110,"setKnockback":0,"baseKnockback":30,"effect":"Slash","hitlagAttacker":0,"hitlagDefender":0,"hitlagAttackerCrouched":0,"hitlagDefenderCrouched":0,"shieldstun":0,"isWeightIndependent":false,"id":4505},{"name":"id1","damage":0,"angle":361,"knockbackGrowth":110,"setKnockback":0,"baseKnockback":30,"effect":"Slash","hitlagAttacker":0,"hitlagDefender":0,"hitlagAttackerCrouched":0,"hitlagDefenderCrouched":0,"shieldstun":0,"isWeightIndependent":false,"id":4506},{"name":"id2","damage":0,"angle":361,"knockbackGrowth":110,"setKnockback":0,"baseKnockback":30,"effect":"Slash","hitlagAttacker":0,"hitlagDefender":0,"hitlagAttackerCrouched":0,"hitlagDefenderCrouched":0,"shieldstun":0,"isWeightIndependent":false,"id":4507}],"start":8,"end":10,"moveId":1533,"id":549}],"totalFrames":29,"iasa":26,"start":8,"end":10,"type":2,"characterId":0,"source":"http://meleeframedata.com/","gifUrl":"https://i.fightcore.gg/beta/bowser/jab2.gif","isInterpolated":false,"sources":[{"name":"Hitboxes from I KneeData","url":"http://ikneedata.com/","id":4},{"name":"GIF by Emilia \"ReelDino\" H","url":"https://drive.google.com/drive/folders/14rcZ8ed43hWOJaxQhHsB-hcAgxWubRaz?usp=sharing","id":1},{"name":"Framedata software by @NeilHarbin0","url":"https://github.com/NeilHarbin0","id":2},{"name":"Base frame data by MeleeFrameData.com","url":"https://meleeframedata.com/","id":3}],"id":1533},{"name":"Koopa Klaw (Air)","normalizedName":"asideb","hits":[],"totalFrames":59,"start":16,"end":18,"type":4,"notes":"scratch can do 12, 10, or 8% damage. when grabbed, bite does 4%, forward throw does 13%, and back throw does 9%","characterId":0,"source":"http://meleeframedata.com/","gifUrl":"https://i.fightcore.gg/beta/bowser/asideb.gif","isInterpolated":false,"sources":[{"name":"Base frame data by MeleeFrameData.com","url":"https://meleeframedata.com/","id":3},{"name":"Framedata software by @NeilHarbin0","url":"https://github.com/NeilHarbin0","id":2},{"name":"GIF by Emilia \"ReelDino\" H","url":"https://drive.google.com/drive/folders/14rcZ8ed43hWOJaxQhHsB-hcAgxWubRaz?usp=sharing","id":1}],"id":1536},{"name":"Bowser Bomb (Air)","normalizedName":"adownb","hits":[],"totalFrames":0,"start":32,"end":0,"type":4,"notes":"active until landing, then 60 frames of endlag","characterId":0,"source":"http://meleeframedata.com/","gifUrl":"https://i.fightcore.gg/beta/bowser/adownb.gif","isInterpolated":false,"sources":[{"name":"GIF by Emilia \"ReelDino\" H","url":"https://drive.google.com/drive/folders/14rcZ8ed43hWOJaxQhHsB-hcAgxWubRaz?usp=sharing","id":1},{"name":"Framedata software by @NeilHarbin0","url":"https://github.com/NeilHarbin0","id":2},{"name":"Base frame data by MeleeFrameData.com","url":"https://meleeframedata.com/","id":3},{"name":"Hitboxes from I KneeData","url":"http://ikneedata.com/","id":4}],"id":1537},{"name":"Whirling Fortress (Air)","normalizedName":"aupb","hits":[],"totalFrames":49,"start":5,"end":46,"type":4,"notes":"can also do 3% damage. all hitboxes connecting will result in 29% damage. able to grab edge 13 frames before freefall if started in the air","characterId":0,"source":"http://meleeframedata.com/","gifUrl":"https://i.fightcore.gg/beta/bowser/aupb.gif","isInterpolated":false,"sources":[{"name":"Hitboxes from I KneeData","url":"http://ikneedata.com/","id":4},{"name":"Base frame data by MeleeFrameData.com","url":"https://meleeframedata.com/","id":3},{"name":"Framedata software by @NeilHarbin0","url":"https://github.com/NeilHarbin0","id":2},{"name":"GIF by Emilia \"ReelDino\" H","url":"https://drive.google.com/drive/folders/14rcZ8ed43hWOJaxQhHsB-hcAgxWubRaz?usp=sharing","id":1}],"id":1538},{"name":"Fire Breath (Air)","normalizedName":"aneutralb","hits":[],"totalFrames":92,"start":23,"end":62,"type":4,"notes":"frames listed are the minimum anmount of frames move will be active (if you quickly tab b)","characterId":0,"source":"http://meleeframedata.com/","gifUrl":"https://i.fightcore.gg/beta/bowser/aneutralb.gif","isInterpolated":false,"sources":[{"name":"GIF by Emilia \"ReelDino\" H","url":"https://drive.google.com/drive/folders/14rcZ8ed43hWOJaxQhHsB-hcAgxWubRaz?usp=sharing","id":1},{"name":"Framedata software by @NeilHarbin0","url":"https://github.com/NeilHarbin0","id":2},{"name":"Base frame data by MeleeFrameData.com","url":"https://meleeframedata.com/","id":3}],"id":1539},{"name":"Grab","normalizedName":"grab","hits":[{"hitboxes":[{"name":"id0","damage":0,"angle":361,"knockbackGrowth":100,"setKnockback":0,"baseKnockback":0,"effect":"Grab","hitlagAttacker":0,"hitlagDefender":0,"hitlagAttackerCrouched":0,"hitlagDefenderCrouched":0,"shieldstun":0,"isWeightIndependent":false,"id":4562},{"name":"id1","damage":0,"angle":361,"knockbackGrowth":100,"setKnockback":0,"baseKnockback":0,"effect":"Grab","hitlagAttacker":0,"hitlagDefender":0,"hitlagAttackerCrouched":0,"hitlagDefenderCrouched":0,"shieldstun":0,"isWeightIndependent":false,"id":4563},{"name":"id2","damage":0,"angle":361,"knockbackGrowth":100,"setKnockback":0,"baseKnockback":0,"effect":"Grab","hitlagAttacker":0,"hitlagDefender":0,"hitlagAttackerCrouched":0,"hitlagDefenderCrouched":0,"shieldstun":0,"isWeightIndependent":false,"id":4564}],"start":8,"end":9,"moveId":1619,"id":576}],"totalFrames":40,"start":9,"end":10,"type":0,"characterId":0,"source":"http://meleeframedata.com/","gifUrl":"https://i.fightcore.gg/beta/bowser/grab.gif","isInterpolated":false,"sources":[{"name":"Base frame data by MeleeFrameData.com","url":"https://meleeframedata.com/","id":3},{"name":"Framedata software by @NeilHarbin0","url":"https://github.com/NeilHarbin0","id":2},{"name":"GIF by Emilia \"ReelDino\" H","url":"https://drive.google.com/drive/folders/14rcZ8ed43hWOJaxQhHsB-hcAgxWubRaz?usp=sharing","id":1}],"id":1619},{"name":"Dashgrab","normalizedName":"dashgrab","hits":[{"hitboxes":[{"name":"id0","damage":0,"angle":361,"knockbackGrowth":100,"setKnockback":0,"baseKnockback":0,"effect":"Grab","hitlagAttacker":0,"hitlagDefender":0,"hitlagAttackerCrouched":0,"hitlagDefenderCrouched":0,"shieldstun":0,"isWeightIndependent":false,"id":4565},{"name":"id1","damage":0,"angle":361,"knockbackGrowth":100,"setKnockback":0,"baseKnockback":0,"effect":"Grab","hitlagAttacker":0,"hitlagDefender":0,"hitlagAttackerCrouched":0,"hitlagDefenderCrouched":0,"shieldstun":0,"isWeightIndependent":false,"id":4566},{"name":"id2","damage":0,"angle":361,"knockbackGrowth":100,"setKnockback":0,"baseKnockback":0,"effect":"Grab","hitlagAttacker":0,"hitlagDefender":0,"hitlagAttackerCrouched":0,"hitlagDefenderCrouched":0,"shieldstun":0,"isWeightIndependent":false,"id":4567}],"start":9,"end":11,"moveId":1620,"id":577}],"totalFrames":50,"start":10,"end":12,"type":0,"characterId":0,"source":"http://meleeframedata.com/","gifUrl":"https://i.fightcore.gg/beta/bowser/dashgrab.gif","isInterpolated":false,"sources":[{"name":"GIF by Emilia \"ReelDino\" H","url":"https://drive.google.com/drive/folders/14rcZ8ed43hWOJaxQhHsB-hcAgxWubRaz?usp=sharing","id":1},{"name":"Framedata software by @NeilHarbin0","url":"https://github.com/NeilHarbin0","id":2},{"name":"Base frame data by MeleeFrameData.com","url":"https://meleeframedata.com/","id":3}],"id":1620},{"name":"Forward Tilt (Up)","normalizedName":"uaft","hits":[],"totalFrames":47,"iasa":37,"start":12,"end":16,"type":1,"characterId":0,"source":"http://meleeframedata.com/","gifUrl":"https://i.fightcore.gg/beta/bowser/uaft.gif","isInterpolated":false,"sources":[{"name":"Base frame data by MeleeFrameData.com","url":"https://meleeframedata.com/","id":3},{"name":"Framedata software by @NeilHarbin0","url":"https://github.com/NeilHarbin0","id":2},{"name":"GIF by Emilia \"ReelDino\" H","url":"https://drive.google.com/drive/folders/14rcZ8ed43hWOJaxQhHsB-hcAgxWubRaz?usp=sharing","id":1},{"name":"Hitboxes from I KneeData","url":"http://ikneedata.com/","id":4}],"id":1636},{"name":"Forward Tilt (Down)","normalizedName":"daft","hits":[],"totalFrames":47,"iasa":37,"start":12,"end":16,"type":1,"characterId":0,"source":"http://meleeframedata.com/","gifUrl":"https://i.fightcore.gg/beta/bowser/daft.gif","isInterpolated":false,"sources":[{"name":"Hitboxes from I KneeData","url":"http://ikneedata.com/","id":4},{"name":"GIF by Emilia \"ReelDino\" H","url":"https://drive.google.com/drive/folders/14rcZ8ed43hWOJaxQhHsB-hcAgxWubRaz?usp=sharing","id":1},{"name":"Framedata software by @NeilHarbin0","url":"https://github.com/NeilHarbin0","id":2},{"name":"Base frame data by MeleeFrameData.com","url":"https://meleeframedata.com/","id":3}],"id":1637},{"name":"Tech-Roll Forward","normalizedName":"ftechroll","hits":[],"totalFrames":40,"type":0,"notes":"Horizontal Movement At: 14\r\nDistance: 13.8 ft\r\nInvincible: 1-20","characterId":0,"source":"https://smashboards.com/threads/detailed-throws-techs-and-getups-frame-data.206469/","isInterpolated":false,"sources":[],"id":1671},{"name":"Tech-Roll Backward","normalizedName":"btechroll","hits":[],"totalFrames":40,"type":0,"notes":"Horizontal Movement At: 8\r\nDistance: 13.6 ft\r\nInvincible: 1-20","characterId":0,"source":"https://smashboards.com/threads/detailed-throws-techs-and-getups-frame-data.206469/","isInterpolated":false,"sources":[],"id":1672},{"name":"Getup-Attack (Back)","normalizedName":"bgetup","hits":[],"totalFrames":49,"type":0,"notes":"Hit: 18-19 (Behind), 25-26 (Front)\r\nInvincible: 1-26","characterId":0,"source":"https://smashboards.com/threads/detailed-throws-techs-and-getups-frame-data.206469/","isInterpolated":false,"sources":[{"name":"Hitboxes from I KneeData","url":"http://ikneedata.com/","id":4}],"id":1673},{"name":"Getup-Attack (Stomach)","normalizedName":"fgetup","hits":[],"totalFrames":49,"type":0,"notes":"Hit: 10-11 (Front), 26-27 (Behind)\r\nInvincible: 1-27","characterId":0,"source":"https://smashboards.com/threads/detailed-throws-techs-and-getups-frame-data.206469/","isInterpolated":false,"sources":[{"name":"Hitboxes from I KneeData","url":"http://ikneedata.com/","id":4}],"id":1674},{"name":"Getup-Roll Forward (Back)","normalizedName":"fgetuprollback","hits":[],"totalFrames":35,"type":0,"notes":"Horizontal Movement At: 16\r\nDistance: 14.2 ft\r\nInvincible: 1-19","characterId":0,"source":"https://smashboards.com/threads/detailed-throws-techs-and-getups-frame-data.206469/","isInterpolated":false,"sources":[],"id":1675},{"name":"Getup-Roll Forward (Stomach)","normalizedName":"fgetuprollstomach","hits":[],"totalFrames":35,"type":0,"notes":"Horizontal Movement At: 13\r\nDistance: 9.4 ft\r\nInvincible: 1-27","characterId":0,"source":"https://smashboards.com/threads/detailed-throws-techs-and-getups-frame-data.206469/","isInterpolated":false,"sources":[],"id":1676},{"name":"Getup-Roll Backward (Back)","normalizedName":"bgetuprollback","hits":[],"totalFrames":35,"type":0,"notes":"Horizontal Movement At: 12\r\nDistance: 13.4 ft\r\nInvincible: 1-27 (If the roll takes you to an edge you will slip off unless an attack is timed on that exact frame)","characterId":0,"source":"https://smashboards.com/threads/detailed-throws-techs-and-getups-frame-data.206469/","isInterpolated":false,"sources":[],"id":1677},{"name":"Getup-Roll Backward (Stomach)","normalizedName":"bgetuprollstomach","hits":[],"totalFrames":35,"type":0,"notes":"Horizontal Movement At: 10\r\nDistance: 9.4 ft\r\nInvincible: 1-19","characterId":0,"source":"https://smashboards.com/threads/detailed-throws-techs-and-getups-frame-data.206469/","isInterpolated":false,"sources":[],"id":1678},{"name":"Tech-Neutral","normalizedName":"neutraltech","hits":[],"totalFrames":26,"type":0,"notes":"Invincible: 1-20","characterId":0,"source":"http://meleeframedata.com/","isInterpolated":false,"sources":[{"name":"Base frame data by MeleeFrameData.com","url":"https://meleeframedata.com/","id":3}],"id":1886},{"name":"Tech-Wall","normalizedName":"walltech","hits":[],"totalFrames":31,"iasa":6,"type":0,"notes":"Invincible: 1-14\r\nInput an upwards direction anywhere on 1-4 for walljump tech on 6)","characterId":0,"source":"http://meleeframedata.com/","isInterpolated":false,"sources":[{"name":"Base frame data by MeleeFrameData.com","url":"https://meleeframedata.com/","id":3}],"id":1912},{"name":"Tech-Wall Jump","normalizedName":"walltechjump","hits":[],"totalFrames":40,"iasa":1,"type":0,"characterId":0,"source":"http://meleeframedata.com/","isInterpolated":false,"sources":[{"name":"Base frame data by MeleeFrameData.com","url":"https://meleeframedata.com/","id":3}],"id":1938}],"characterStatistics":{"id":34,"weight":117,"gravity":1.9,"walkSpeed":0.65,"runSpeed":1.5,"waveDashLengthRank":13,"plaIntangibilityFrames":8,"jumpSquat":8,"canWallJump":false,"notes":"","initialDash":1.06,"dashFrames":13,"waveDashLength":35.49},"characterInfo":{"id":7,"discord":"https://discord.com/invite/4jpjZkB","meleeFrameData":"http://meleeframedata.com/bowser","ssbWiki":"https://www.ssbwiki.com/Bowser_(SSBM)"},"id":34}